{
  "project_info": {
    "project_number": "158343388699",
    "firebase_url": "https://petasosexpress-5fde0-default-rtdb.firebaseio.com",
    "project_id": "petasosexpress-5fde0",
    "storage_bucket": "petasosexpress-5fde0.appspot.com"
  },
  "client": [
    {
      "client_info": {
        "mobilesdk_app_id": "1:158343388699:android:65bfdd57ade1b208c4e2be",
        "android_client_info": {
          "package_name": "ca.hermeslogistics.itservices.petasosexpress"
        }
      },
      "oauth_client": [
        {
          "client_id": "158343388699-kuilj6tonjimjvnsmmsj74567nmv3hpd.apps.googleusercontent.com",
          "client_type": 1,
          "android_info": {
            "package_name": "ca.hermeslogistics.itservices.petasosexpress",
            "certificate_hash": "6154d2867d6455307a8c5217664f770136791fb7"
          }
        },
        {
          "client_id": "158343388699-2hte71l6b7mjtu9dlrgsi6muko9nf26p.apps.googleusercontent.com",
          "client_type": 3
        }
      ],
      "api_key": [
        {
          "current_key": "AIzaSyD9HQTULDooH5_1aCABcxu3JwJq48m7YyU"
        }
      ],
      "services": {
        "appinvite_service": {
          "other_platform_oauth_client": [
            {
              "client_id": "158343388699-2hte71l6b7mjtu9dlrgsi6muko9nf26p.apps.googleusercontent.com",
              "client_type": 3
            }
          ]
        }
      }
    }
  ],
  "configuration_version": "1"
}